create_flask_vps_app/__init__.py
create_flask_vps_app/main.py
create_flask_vps_app/templates/README.md
create_flask_vps_app/templates/fabfile.py
create_flask_vps_app/templates/requirements.txt
create_flask_vps_app/templates/app/__init__.py
create_flask_vps_app/templates/app/cors.py
create_flask_vps_app/templates/app/db.py
create_flask_vps_app/templates/app/main.py
create_flask_vps_app/templates/templates/nginx_config.j2
create_flask_vps_app/templates/templates/systemd_service.j2
create_flask_vps_app-0.7.0.dist-info/METADATA
create_flask_vps_app-0.7.0.dist-info/WHEEL
create_flask_vps_app-0.7.0.dist-info/entry_points.txt
create_flask_vps_app-0.7.0.dist-info/top_level.txt
create_flask_vps_app-0.7.0.dist-info/RECORD
