Metadata-Version: 2.4
Name: create-flask-vps-app
Version: 0.7.0
Summary: A CLI tool to scaffold a Flask API project with deployment setup.
Home-page: https://github.com/al3rez/create-flask-vps-app
Author: Alireza Bashiri
Author-email: al3rez@gmail.com
Requires-Python: >=3.6
Requires-Dist: jinja2
Requires-Dist: flask
Requires-Dist: python-dotenv
Requires-Dist: fabric
Requires-Dist: gunicorn
Requires-Dist: flask-cors
Dynamic: author
Dynamic: author-email
Dynamic: description
Dynamic: description-content-type
Dynamic: home-page
Dynamic: requires-dist
Dynamic: requires-python
Dynamic: summary
